matlab_python_interop/__init__.py
matlab_python_interop-0.0.0.dist-info/LICENSE
matlab_python_interop-0.0.0.dist-info/WHEEL
matlab_python_interop-0.0.0.dist-info/METADATA
matlab_python_interop-0.0.0.dist-info/RECORD
